browsers_detector/__init__.py
browsers_detector/browsers_detector.py
browsers_detector/example.py
browsers_detector/data/__init__.py
browsers_detector/data/chrome_desktop.JPG
browsers_detector/data/chrome_taskbar.JPG
browsers_detector/data/edge_desktop.JPG
browsers_detector/data/edge_taskbar.JPG
browsers_detector/data/firefox_desktop.JPG
browsers_detector/data/firefox_taskbar.JPG
browsers_detector/data/opera_desktop.JPG
browsers_detector/data/opera_taskbar.JPG
browsers_detector/data/screenshots/__init__.py
browsers_detector/data/templates/__init__.py
TemplateMatchResearch-2.0.dist-info/LICENSE
TemplateMatchResearch-2.0.dist-info/METADATA
TemplateMatchResearch-2.0.dist-info/WHEEL
TemplateMatchResearch-2.0.dist-info/top_level.txt
TemplateMatchResearch-2.0.dist-info/RECORD
