Metadata-Version: 2.1
Name: TemplateMatchResearch
Version: 2.0
Summary: A lightweight package to detect chrome, firefox, edge, and opera browser on a windows user's computer
Home-page: https://github.com/emire1/TemplateMactchResearch
Author: Emmanuel Mireku
Author-email: emmanuelmireku15@gmail.com
License: UNKNOWN
Platform: UNKNOWN
Classifier: Programming Language :: Python :: 3
Classifier: License :: OSI Approved :: MIT License
Classifier: Operating System :: Microsoft :: Windows
Requires-Python: >=3.6
Requires-Dist: opencv-python
Requires-Dist: pyautogui
Requires-Dist: numpy
Requires-Dist: imutils
